computer_graphics_demo/__init__.py
computer_graphics_demo/__main__.py
computer_graphics_demo/_version.py
computer_graphics_demo/b.py
computer_graphics_demo/bezier.py
computer_graphics_demo/ellipse.py
computer_graphics_demo/fern.py
computer_graphics_demo/julia.py
computer_graphics_demo/koch.py
computer_graphics_demo/mandelbrot.py
computer_graphics_demo/reality.py
computer_graphics_demo/utils.py
computer_graphics_demo/circle/__init__.py
computer_graphics_demo/circle/bresenham.py
computer_graphics_demo/circle/midpoint.py
computer_graphics_demo/fill/__init__.py
computer_graphics_demo/fill/scan.py
computer_graphics_demo/fill/seed.py
computer_graphics_demo/line/__init__.py
computer_graphics_demo/line/bresenham.py
computer_graphics_demo/line/midpoint.py
computer_graphics_demo-0.3.dist-info/LICENSE
computer_graphics_demo-0.3.dist-info/METADATA
computer_graphics_demo-0.3.dist-info/WHEEL
computer_graphics_demo-0.3.dist-info/entry_points.txt
computer_graphics_demo-0.3.dist-info/top_level.txt
computer_graphics_demo-0.3.dist-info/RECORD
