Metadata-Version: 2.1
Name: computer-graphics-demo
Version: 0.3
Summary: A demonstration of computer graphics.
Author-email: Wu Zhenyu <wuzy01@qq.com>
License: GPL v3
Project-URL: Homepage, https://pypi.org/project/computer-graphics-demo/
Project-URL: Download, https://github.com/Freed-Wu/computer-graphics-homework/releases
Project-URL: Bug Report, https://github.com/Freed-Wu/computer-graphics-homework/issues
Project-URL: Source, https://github.com/Freed-Wu/computer-graphics-homework
Keywords: computer graphics
Classifier: Development Status :: 3 - Alpha
Classifier: Intended Audience :: Developers
Classifier: Topic :: Software Development :: Build Tools
Classifier: License :: OSI Approved :: GNU General Public License v3 (GPLv3)
Classifier: Operating System :: Microsoft :: Windows
Classifier: Operating System :: POSIX
Classifier: Operating System :: Unix
Classifier: Operating System :: MacOS
Classifier: Programming Language :: Python :: 3 :: Only
Classifier: Programming Language :: Python :: 3
Classifier: Programming Language :: Python :: 3.6
Classifier: Programming Language :: Python :: 3.7
Classifier: Programming Language :: Python :: 3.8
Classifier: Programming Language :: Python :: 3.9
Requires-Python: <3.10,>=3.6
License-File: LICENSE
Requires-Dist: docopt
Requires-Dist: taichi (<0.8,>=0.7)
Provides-Extra: dev
Requires-Dist: get-version ; extra == 'dev'
Requires-Dist: pytest ; extra == 'dev'
Requires-Dist: rich ; extra == 'dev'
